smb2_gym/__init__.py
smb2_gym/actions.py
smb2_gym/play_human.py
smb2_gym/py.typed
smb2_gym/smb2_env.py
smb2_gym/_nes/prg0/super_mario_bros_2_prg0.nes
smb2_gym/_nes/prg0/saves/luigi/1-1.sav
smb2_gym/_nes/prg0/saves/mario/1-1.sav
smb2_gym/_nes/prg0/saves/mario/1-2.sav
smb2_gym/_nes/prg0/saves/mario/1-3.sav
smb2_gym/_nes/prg0/saves/mario/2-1.sav
smb2_gym/_nes/prg0/saves/mario/4-1.sav
smb2_gym/_nes/prg0/saves/peach/1-1.sav
smb2_gym/_nes/prg0/saves/select/1-2.sav
smb2_gym/_nes/prg0/saves/select/1-3.sav
smb2_gym/_nes/prg0/saves/select/2-1.sav
smb2_gym/_nes/prg0/saves/select/2-2.sav
smb2_gym/_nes/prg0/saves/select/2-3.sav
smb2_gym/_nes/prg0/saves/select/3-1.sav
smb2_gym/_nes/prg0/saves/select/5-1.sav
smb2_gym/_nes/prg0/saves/select/5-2.sav
smb2_gym/_nes/prg0/saves/select/5-3.sav
smb2_gym/_nes/prg0/saves/select/7-1.sav
smb2_gym/_nes/prg0/saves/select/7-2.sav
smb2_gym/_nes/prg0/saves/toad/1-1.sav
smb2_gym/_nes/prg0_edited/super_mario_bros_2_prg0_edited.nes
smb2_gym/_nes/prg0_edited/saves/easy_combined_curriculum.sav
smb2_gym/app/__init__.py
smb2_gym/app/info_display.py
smb2_gym/app/keyboard.py
smb2_gym/app/play_display.py
smb2_gym/app/rendering.py
smb2_gym/constants/__init__.py
smb2_gym/constants/character_stats.py
smb2_gym/constants/object_ids.py
smb2_gym/constants/ram.py
smb2_gym/constants/semantic.py
smb2_gym/state/__init__.py
smb2_gym/state/_base.py
smb2_gym/state/enemies.py
smb2_gym/state/player.py
smb2_gym/state/position.py
smb2_gym/state/semantic_map.py
smb2_gym-0.2.14.dist-info/METADATA
smb2_gym-0.2.14.dist-info/WHEEL
smb2_gym-0.2.14.dist-info/entry_points.txt
smb2_gym-0.2.14.dist-info/top_level.txt
smb2_gym-0.2.14.dist-info/RECORD
