Metadata-Version: 2.4
Name: smb2-gym
Version: 0.2.14
Summary: Super Mario Bros 2 (Europe) Gymnasium Environment
Author: Alexei Quick
License: MIT
Project-URL: Homepage, https://github.com/alexeiquickcode/smb2-gym
Project-URL: Bug Tracker, https://github.com/alexeiquickcode/smb2-gym/issues
Classifier: Development Status :: 3 - Alpha
Classifier: Intended Audience :: Science/Research
Classifier: Operating System :: OS Independent
Classifier: Programming Language :: Python :: 3
Classifier: Programming Language :: Python :: 3.8
Classifier: Programming Language :: Python :: 3.9
Classifier: Programming Language :: Python :: 3.10
Classifier: Programming Language :: Python :: 3.11
Classifier: Programming Language :: Python :: 3.12
Classifier: Programming Language :: Python :: 3.13
Classifier: Topic :: Scientific/Engineering :: Artificial Intelligence
Requires-Python: >=3.8
Requires-Dist: setuptools<67.3.0
Requires-Dist: gymnasium>=0.29.0
Requires-Dist: numpy>=1.21.0
Requires-Dist: pygame>=2.1.0
Requires-Dist: tetanes-py==0.1.9
Provides-Extra: dev
Requires-Dist: pytest; extra == "dev"
Requires-Dist: isort; extra == "dev"
Requires-Dist: yapf; extra == "dev"
Requires-Dist: basedpyright; extra == "dev"
